{
  "globalParams": {
    "type": "supervised"
  },
  "database": {
    "dbPath": "data/ogle3/ogle3_processed.db"
  },
  "loadData": {
    "params": {
      "dataName": "ogle3",
      "relativePath": "data/ogle3/ogle3.csv",
      "skip": false
    }
  },
  "modelSelection": {
    "function": "grid",
    "params": {
    }
  },
  "serialization": {
    "params": {
      "modelLoadPath": null,
      "modelSavePath": "/Users/ryanjmccall/code/light_curve_ml/models/ogle3/supervised/rf-classifier-ogle3.pkl",
      "imgPath": "/Users/ryanjmccall/code/light_curve_ml/models/ogle3/supervised"
    }
  }
}
